{
  "apps": [{
      "name": "flashman",
      "script": "bin/www",
      "log_date_format": "YYYY-MM-DD HH:mm Z",
      "autorestart": false,
      "env": {
        "production": false,
        "TZ": "America/Sao_Paulo",
        "FLM_IMG_RELEASE_DIR": "./public/firmwares/",
        "FLM_ALLOW_DEV_UPDATE_REST_DATA": false,
        "FLM_MONGODB_HOST": "localhost",
        "FLM_ADM_USER": "admin",
        "FLM_ADM_PASS": "landufrj123",
	"FLM_MQTTS_DOMAIN": "192.168.15.42",
	"FLM_MQTT_PORT": "5000",
	"FLM_COMPANY_SECRET": "eEIBDRfEao1JriwsKGyN6l1WVzWZMmcr",
        "FLM_CERT_MQTT_DIR": "./certs"
      },
      "error_file": "/dev/stderr",
      "out_file": "/dev/stdout",
      "exec_mode": "cluster"
    }]
}
